packetwhiz/__init__.py
packetwhiz/__main__.py
packetwhiz_nfa-0.1.0.dist-info/licenses/LICENSE
packetwhiz_nfa-0.1.0.dist-info/METADATA
packetwhiz_nfa-0.1.0.dist-info/WHEEL
packetwhiz_nfa-0.1.0.dist-info/entry_points.txt
packetwhiz_nfa-0.1.0.dist-info/top_level.txt
packetwhiz_nfa-0.1.0.dist-info/RECORD
