Metadata-Version: 2.4
Name: packetwhiz-nfa
Version: 0.1.0
Summary: PacketWhiz — Network Forensics & Analysis (NFA) toolkit
Author: Omar Tamer, Farida Ismail
License: MIT License
Project-URL: Homepage, https://github.com/Omar-tamerr/Packet-Whiz
Keywords: pcap,network,forensics,security,tshark,wireshark,ctf
Classifier: Programming Language :: Python :: 3
Classifier: Programming Language :: Python :: 3 :: Only
Classifier: Programming Language :: Python :: 3.9
Classifier: Programming Language :: Python :: 3.10
Classifier: Programming Language :: Python :: 3.11
Classifier: Programming Language :: Python :: 3.12
Classifier: License :: OSI Approved :: MIT License
Classifier: Operating System :: OS Independent
Classifier: Environment :: Console
Classifier: Topic :: Security
Classifier: Topic :: Internet
Classifier: Intended Audience :: Information Technology
Classifier: Intended Audience :: System Administrators
Requires-Python: >=3.9
License-File: LICENSE
Requires-Dist: pyshark>=0.6
Requires-Dist: rich>=13.7
Requires-Dist: jinja2>=3.1
Dynamic: license-file
